{
    "bboxes": [
        [
            0.37233017339939023,
            0.4074372379954268,
            0.6509021889291159,
            0.9957087223704268
        ],
        [
            0.37233017339939023,
            0.4074372379954268,
            0.6509021889291159,
            0.9957087223704268
        ],
        [
            0.2589926817358994,
            0.7937041491996951,
            0.4532265267721037,
            0.958573027820122
        ],
        [
            0.37268197408536585,
            0.40776685761242376,
            0.6509891863567073,
            0.6999427162728659
        ],
        [
            0.3816887087938262,
            0.45806250595464937,
            0.6445531035632622,
            0.697333984375
        ],
        [
            0.001804947969390125,
            0.16155124571265245,
            0.6501243330792683,
            0.994891982660061
        ],
        [
            0.37249342011242376,
            0.4079743473704268,
            0.6510758265053354,
            0.6996927400914634
        ],
        [
            0.3816887087938262,
            0.45806250595464937,
            0.6445531035632622,
            0.697333984375
        ]
    ],
    "labels": [
        " wine",
        " bottle",
        " grapefruit",
        " drawing",
        " drawing",
        " pour",
        " wine bottle",
        " wine bottle"
    ],
    "scores": [
        0.8082525730133057,
        0.8079652786254883,
        0.33125928044319153,
        0.23763665556907654,
        0.22448697686195374,
        0.20938391983509064,
        0.20838885009288788,
        0.20102393627166748
    ],
    "model_info": {
        "model_config": "/mnt/sda/miatang/projects/stroke-label/extern/mmdetection/ours_weights/base_cat_full_ft_allclass_val/intersect_full_ft_all_class_val.py",
        "weights": "/mnt/sda/miatang/projects/stroke-label/extern/mmdetection/ours_weights/base_cat_full_ft_allclass_val/best_coco_bbox_mAP_iter_47000.pth",
        "device": "cuda:0",
        "score_threshold": 0.2
    }
}